BlessedCrack/Blessed_Crack.py
BlessedCrack/__init__.py
BlessedCrack-0.1.dist-info/METADATA
BlessedCrack-0.1.dist-info/WHEEL
BlessedCrack-0.1.dist-info/entry_points.txt
BlessedCrack-0.1.dist-info/top_level.txt
BlessedCrack-0.1.dist-info/RECORD
